sirbot/plugins/__init__.py
sirbot/plugins/__meta__.py
sirbot/plugins/candy.py
sirbot/plugins/config.yml
sirbot/plugins/giphy.py
sirbot/plugins/pypi.py
sirbot/plugins/scheduler.py
sirbot/plugins/sqlite.py
sirbot/plugins/github/__init__.py
sirbot/plugins/github/errors.py
sirbot/plugins/github/github.py
sirbot.plugins-0.2.0.dist-info/DESCRIPTION.rst
sirbot.plugins-0.2.0.dist-info/METADATA
sirbot.plugins-0.2.0.dist-info/RECORD
sirbot.plugins-0.2.0.dist-info/WHEEL
sirbot.plugins-0.2.0.dist-info/metadata.json
sirbot.plugins-0.2.0.dist-info/top_level.txt
